ZvolvArithmetic/__init__.py
ZvolvArithmetic/arithmetic_opertion.py
ZvArithmetic5-0.1.0.dist-info/LICENSE
ZvArithmetic5-0.1.0.dist-info/METADATA
ZvArithmetic5-0.1.0.dist-info/WHEEL
ZvArithmetic5-0.1.0.dist-info/top_level.txt
ZvArithmetic5-0.1.0.dist-info/RECORD
