Metadata-Version: 2.1
Name: ZvArithmetic5
Version: 0.1.0
Summary: Official Zv Arithmetic Python SDK
Home-page: https://github.com/zvolvapi/python-zvolv-sdk
Download-URL: https://github.com/zvapi/python-zv-sdk/archive/refs/heads/main.zip
Author: Yogesh Jadhav
Author-email: support@zv.com
License: MIT
Project-URL: Source, https://github.com/zvolv/python-zvolv-sdk
Keywords: zv,zv-api,web-api,sdk,rest-api-client
Classifier: Development Status :: 3 - Alpha
Classifier: Intended Audience :: Developers
Classifier: Topic :: Software Development :: Build Tools
Classifier: Operating System :: OS Independent
Classifier: License :: OSI Approved :: MIT License
Classifier: Programming Language :: Python :: 3
Classifier: Programming Language :: Python :: 3.6
Classifier: Programming Language :: Python :: 3.7
Classifier: Programming Language :: Python :: 3.8
Classifier: Programming Language :: Python :: 3.9
Classifier: Programming Language :: Python :: 3.10
Classifier: Programming Language :: Python :: 3.11
Requires-Python: >=3.0.1
License-File: LICENSE
